llama_index/readers/pdb/__init__.py
llama_index/readers/pdb/base.py
llama_index/readers/pdb/utils.py
llama_index_readers_pdb-0.4.1.dist-info/METADATA
llama_index_readers_pdb-0.4.1.dist-info/WHEEL
llama_index_readers_pdb-0.4.1.dist-info/licenses/LICENSE
llama_index_readers_pdb-0.4.1.dist-info/RECORD
