Metadata-Version: 2.4
Name: llama-index-readers-pdb
Version: 0.4.1
Summary: llama-index readers pdb integration
Author-email: Your Name <you@example.com>
Maintainer: joshuakto
License-Expression: MIT
License-File: LICENSE
Keywords: Protein Data Bank,academic papers,pdb,proteins
Requires-Python: <4.0,>=3.9
Requires-Dist: llama-index-core<0.15,>=0.13.0
Requires-Dist: requests<3,>=2.31.0
